.aubio_ledfx.mesonpy.libs/libaubio.so.5.4.8
.aubio_ledfx.mesonpy.libs/pkgconfig/aubio.pc
aubio/__init__.py
aubio/_aubio.cpython-313-aarch64-linux-gnu.so
aubio/cmd.py
aubio/cut.py
aubio/midiconv.py
aubio/slicing.py
aubio_ledfx-0.4.11.data/headers/aubio/aubio.h
aubio_ledfx-0.4.11.data/headers/aubio/cvec.h
aubio_ledfx-0.4.11.data/headers/aubio/fmat.h
aubio_ledfx-0.4.11.data/headers/aubio/fvec.h
aubio_ledfx-0.4.11.data/headers/aubio/lvec.h
aubio_ledfx-0.4.11.data/headers/aubio/mathutils.h
aubio_ledfx-0.4.11.data/headers/aubio/musicutils.h
aubio_ledfx-0.4.11.data/headers/aubio/types.h
aubio_ledfx-0.4.11.data/headers/aubio/vecutils.h
aubio_ledfx-0.4.11.data/headers/aubio/effects/pitchshift.h
aubio_ledfx-0.4.11.data/headers/aubio/effects/timestretch.h
aubio_ledfx-0.4.11.data/headers/aubio/io/audio_unit.h
aubio_ledfx-0.4.11.data/headers/aubio/io/ioutils.h
aubio_ledfx-0.4.11.data/headers/aubio/io/sink.h
aubio_ledfx-0.4.11.data/headers/aubio/io/sink_apple_audio.h
aubio_ledfx-0.4.11.data/headers/aubio/io/sink_sndfile.h
aubio_ledfx-0.4.11.data/headers/aubio/io/sink_wavwrite.h
aubio_ledfx-0.4.11.data/headers/aubio/io/source.h
aubio_ledfx-0.4.11.data/headers/aubio/io/source_apple_audio.h
aubio_ledfx-0.4.11.data/headers/aubio/io/source_avcodec.h
aubio_ledfx-0.4.11.data/headers/aubio/io/source_sndfile.h
aubio_ledfx-0.4.11.data/headers/aubio/io/source_wavread.h
aubio_ledfx-0.4.11.data/headers/aubio/notes/notes.h
aubio_ledfx-0.4.11.data/headers/aubio/onset/onset.h
aubio_ledfx-0.4.11.data/headers/aubio/onset/peakpicker.h
aubio_ledfx-0.4.11.data/headers/aubio/pitch/pitch.h
aubio_ledfx-0.4.11.data/headers/aubio/pitch/pitchfcomb.h
aubio_ledfx-0.4.11.data/headers/aubio/pitch/pitchmcomb.h
aubio_ledfx-0.4.11.data/headers/aubio/pitch/pitchschmitt.h
aubio_ledfx-0.4.11.data/headers/aubio/pitch/pitchspecacf.h
aubio_ledfx-0.4.11.data/headers/aubio/pitch/pitchyin.h
aubio_ledfx-0.4.11.data/headers/aubio/pitch/pitchyinfast.h
aubio_ledfx-0.4.11.dist-info/METADATA
aubio_ledfx-0.4.11.dist-info/WHEEL
aubio_ledfx-0.4.11.dist-info/entry_points.txt
aubio_ledfx-0.4.11.dist-info/RECORD
