Metadata-Version: 2.1
Name: aubio-ledfx
Version: 0.4.11
Summary: A collection of tools for music analysis
Author-Email: Paul Brossier <piem@aubio.org>
Maintainer-Email: LedFx Team <hello@ledfx.app>
License: GNU/GPL version 3
Classifier: Development Status :: 4 - Beta
Classifier: Environment :: Console
Classifier: Intended Audience :: Science/Research
Classifier: Topic :: Software Development :: Libraries
Classifier: Topic :: Multimedia :: Sound/Audio :: Analysis
Classifier: Topic :: Multimedia :: Sound/Audio :: Sound Synthesis
Classifier: Operating System :: POSIX
Classifier: Operating System :: MacOS :: MacOS X
Classifier: Operating System :: Microsoft :: Windows
Classifier: Programming Language :: C
Classifier: Programming Language :: Python
Classifier: License :: OSI Approved :: GNU General Public License v3 or later (GPLv3+)
Project-URL: Homepage, https://aubio.org/
Project-URL: Repository, https://github.com/aubio/aubio
Project-URL: Documentation, https://aubio.org/manual/latest/
Requires-Python: >=3.8
Requires-Dist: numpy>=1.26.4; platform_system != "Darwin" and platform_machine != "aarch64"
Requires-Dist: numpy>=2.0.0; platform_system == "Darwin" and platform_machine == "aarch64"
